<?xml version="1.0" encoding="utf-8"?><CardDefinition xmlns:xsd="http://www.w3.org/2001/XMLSchema" xmlns:xsi="http://www.w3.org/2001/XMLSchema-instance" ID="343faaa3-fde9-410e-97ba-b94fd1e12af8" Alias="currency" Schema="tent" Version="1" SingleTone="false"><Name><LocalizedString Language="ru">Справочник валют</LocalizedString></Name><Sections><Section Alias="currency" AddHistory="false" AddWhoInfo="false" Type="coll" ID="1570838f-c8b2-4146-a50b-31bf7f99f73e"><Name><LocalizedString Language="ru">Валюты</LocalizedString></Name><Field Alias="code" ID="553be76c-f22b-4e94-8837-8a137a3c8718" Type="string" Max="10" NotNull="true" IsBrief="true"><Name><LocalizedString Language="ru">Код</LocalizedString></Name></Field><Field Alias="name" ID="7d9f24d7-def1-43a4-a982-fec5068deb51" Type="string" Max="255" NotNull="true"><Name><LocalizedString Language="ru">Название</LocalizedString></Name></Field></Section></Sections></CardDefinition>